int_date.py
int_date-0.2.0.dist-info/LICENSE.txt
int_date-0.2.0.dist-info/METADATA
int_date-0.2.0.dist-info/WHEEL
int_date-0.2.0.dist-info/top_level.txt
int_date-0.2.0.dist-info/RECORD
