Metadata-Version: 2.1
Name: int-date
Version: 0.2.0
Summary: Utility for int date like 20150312.
Home-page: https://github.com/jealous/int_date
Author: Cedric Zhuang
Author-email: cedric.zhuang@gmail.com
License: BSD
Keywords: date integer
Platform: any
Classifier: Programming Language :: Python
Classifier: Natural Language :: English
Classifier: Intended Audience :: Developers
Classifier: Operating System :: OS Independent
Classifier: Development Status :: 4 - Beta
Classifier: Topic :: Utilities
Classifier: License :: OSI Approved :: BSD License
License-File: LICENSE.txt
Requires-Dist: six (>=1.9.0)
Requires-Dist: python-dateutil (>=2.4.2)
